decoder_3_to_8/decoder_3_to_8.v
module decoder_3_to_8(a,b,c,en,y);

    input a,b,c;
    input en;
    output [7:0] y;
    
    assign y[0] = (~a)&(~b)&(~c)&(en);
    assign y[1] = (~a)&(~b)&(c)&(en);
    assign y[2] = (~a)&(b)&(~c)&(en);
    assign y[3] = (~a)&(b)&(c)&(en);
    assign y[4] = (a)&(~b)&(~c)&(en);
    assign y[5] = (a)&(~b)&(c)&(en);
    assign y[6] = (a)&(b)&(~c)&(en);
    assign y[7] = (a)&(b)&(c)&(en);
    
endmodule

decoder_3_to_8/decoder_3_to_8_tb.v
module decoder_3_to_8_tb;

    reg x,y,z,en;
    wire [7:0] w;

    decoder_3_to_8 DUT(x,y,z,en,w);

    initial begin
        $dumpfile("decoder.vcd");
        $dumpvars(0,decoder_3_to_8_tb);
        x=x; y=x; z=x; en=0;
        #10 x=x; y=x; z=x; en=1;
        #10 x=0; y=0; z=0; en=0;
        #10 x=0; y=0; z=0; en=1;
        #10 x=0; y=0; z=1; en=1;
        #10 x=0; y=1; z=0; en=1;
        #10 x=0; y=1; z=1; en=1;
        #10 x=1; y=0; z=0; en=1;
        #10 x=1; y=0; z=1; en=1;
        #10 x=1; y=1; z=0; en=1;
        #10 x=1; y=1; z=1; en=1;
        #10 $finish;
    end

    initial begin
        $monitor("t=%3d, x=%d, y=%d, z=%d, en=%d, w[0]=%d, w[1]=%d, w[2]=%d, w[3]=%d, w[4]=%d, w[5]=%d, w[6]=%d, w[7]=%d", $time, x,y,z,en,w[0],w[1],w[2],w[3],w[4],w[5],w[6],w[7]);
    end

endmodule

decoder_3_to_8/decoder.vcd
$date
	Wed Feb 12 23:55:01 2025
$end
$version
	Icarus Verilog
$end
$timescale
	1s
$end
$scope module decoder_3_to_8_tb $end
$var wire 8 ! w [7:0] $end
$var reg 1 " en $end
$var reg 1 # x $end
$var reg 1 $ y $end
$var reg 1 % z $end
$scope module DUT $end
$var wire 1 # a $end
$var wire 1 $ b $end
$var wire 1 % c $end
$var wire 1 " en $end
$var wire 8 & y [7:0] $end
$upscope $end
$upscope $end
$enddefinitions $end
#0
$dumpvars
b0 &
x%
x$
x#
0"
b0 !
$end
#10
bx !
bx &
1"
#20
b0 !
b0 &
0"
0%
0$
0#
#30
b1 !
b1 &
1"
#40
b10 !
b10 &
1%
#50
b100 !
b100 &
0%
1$
#60
b1000 !
b1000 &
1%
#70
b10000 !
b10000 &
0%
0$
1#
#80
b100000 !
b100000 &
1%
#90
b1000000 !
b1000000 &
0%
1$
#100
b10000000 !
b10000000 &
1%
