logic_gates_1/lg_1.v
`timescale 1ns / 1ps
//////////////////////////////////////////////////////////////////////////////////
// Company: 
// Engineer: 
// 
// Create Date: 02/02/2025 02:40:28 PM
// Design Name: 
// Module Name: logic_gates_1
// Project Name: 
// Target Devices: 
// Tool Versions: 
// Description: 
// 
// Dependencies: 
// 
// Revision:
// Revision 0.01 - File Created
// Additional Comments:
// 
//////////////////////////////////////////////////////////////////////////////////


module logic_gates_1(a,b,c,d,e,f,y);

input a,b,c,d,e,f;
output y;
wire t1,t2,t3,y;
nand #1 G1(t1,a,b);
//      G4(y,t1,t2,t3);
and #2 G2(t2,c,~b,d);
nor #1 G3(t3,e,f);
nand #1 G4(y,t1,t2,t3);

endmodule

logic_gates_1/lg_1_tb.v
`timescale 1ns / 1ps
//////////////////////////////////////////////////////////////////////////////////
// Company: 
// Engineer: 
// 
// Create Date: 02/02/2025 02:44:46 PM
// Design Name: 
// Module Name: logic_gates_1_tb
// Project Name: 
// Target Devices: 
// Tool Versions: 
// Description: 
// 
// Dependencies: 
// 
// Revision:
// Revision 0.01 - File Created
// Additional Comments:
// 
//////////////////////////////////////////////////////////////////////////////////


module lg_1_tb;

reg a,b,c,d,e,f;
wire y;
logic_gates_1  DUT(a,b,c,d,e,f,y);

initial
    begin
        $dumpfile("lg_1.vcd");
	$dumpvars(0,lg_1_tb);
	$monitor($time,
        "a=%b, b=%b, c=%b, d=%b, e=%b, f=%b, y=%b",
        a,b,c,d,e,f,y);
        #5 a=1; b=0; c=0; d=1; e=0; f=0;
        #5 a=0; b=0; c=1; d=1; e=0; f=0;
        #5 a=1; c=0;
        #5 f=1;
        #5 $finish;
    end   

endmodule

logic_gates_1/lg_1.vcd
$date
	Mon Feb  3 17:57:00 2025
$end
$version
	Icarus Verilog
$end
$timescale
	1ps
$end
$scope module lg_1_tb $end
$var wire 1 ! y $end
$var reg 1 " a $end
$var reg 1 # b $end
$var reg 1 $ c $end
$var reg 1 % d $end
$var reg 1 & e $end
$var reg 1 ' f $end
$scope module DUT $end
$var wire 1 " a $end
$var wire 1 # b $end
$var wire 1 $ c $end
$var wire 1 % d $end
$var wire 1 & e $end
$var wire 1 ' f $end
$var wire 1 ( t1 $end
$var wire 1 ) t2 $end
$var wire 1 * t3 $end
$var wire 1 ! y $end
$upscope $end
$upscope $end
$enddefinitions $end
#0
$dumpvars
x*
x)
x(
x'
x&
x%
x$
x#
x"
x!
$end
#5000
0'
0&
1%
0$
0#
1"
#6000
1*
1(
#7000
0)
#8000
1!
#10000
1$
0"
#12000
1)
#13000
0!
#15000
0$
1"
#17000
0)
#18000
1!
#20000
1'
#21000
0*
